pwninit.py
pwninit-0.1.8.dist-info/entry_points.txt
pwninit-0.1.8.dist-info/WHEEL
pwninit-0.1.8.dist-info/METADATA
pwninit-0.1.8.dist-info/RECORD
